AUTHORS
LICENSE
MANIFEST.in
README.rst
setup.py
django_smart_slug.egg-info/PKG-INFO
django_smart_slug.egg-info/SOURCES.txt
django_smart_slug.egg-info/dependency_links.txt
django_smart_slug.egg-info/top_level.txt
smart_slug/__init__.py
smart_slug/fields.py
smart_slug/tests/__init__.py
smart_slug/tests/models.py
smart_slug/tests/settings.py
smart_slug/tests/tests.py