Metadata-Version: 1.0
Name: django-smart-slug
Version: 0.1.0
Summary: a smart slug field for your models
Home-page: http://github.com/coleifer/django-smart-slug/tree/master
Author: Charles Leifer
Author-email: coleifer@gmail.com
License: UNKNOWN
Platform: UNKNOWN
Classifier: Development Status :: 4 - Beta
Classifier: Environment :: Web Environment
Classifier: Intended Audience :: Developers
Classifier: License :: OSI Approved :: MIT License
Classifier: Operating System :: OS Independent
Classifier: Programming Language :: Python
Classifier: Framework :: Django
